sapnmeterdata/__init__.py
sapnmeterdata/functions.py
sapnmeterdata-0.2.0.dist-info/licenses/LICENSE
sapnmeterdata-0.2.0.dist-info/METADATA
sapnmeterdata-0.2.0.dist-info/WHEEL
sapnmeterdata-0.2.0.dist-info/top_level.txt
sapnmeterdata-0.2.0.dist-info/RECORD
