Metadata-Version: 2.4
Name: sapnmeterdata
Version: 0.2.0
Summary: retrive meterdata from SA Power Networks
Author: bfulham
Author-email: Brady Fulham <bfulham@bradyfulham.com>
License-Expression: MIT
Project-URL: Homepage, https://github.com/bfulham/sapnmeterdata
Project-URL: Issues, https://github.com/bfulham/sapnmeterdata/issues
Classifier: Programming Language :: Python :: 3
Classifier: Operating System :: OS Independent
Requires-Python: >=3.9
License-File: LICENSE
Requires-Dist: nemreader
Requires-Dist: bs4
Dynamic: author
Dynamic: license-file
